LICENSE.txt
setup.py
StableRLS.egg-info/PKG-INFO
StableRLS.egg-info/SOURCES.txt
StableRLS.egg-info/dependency_links.txt
StableRLS.egg-info/requires.txt
StableRLS.egg-info/top_level.txt
stablerls/__init__.py
stablerls/configreader.py
stablerls/createFMU.py
stablerls/fmutools.py
stablerls/getports.m
stablerls/gymFMU.py